pdx/__init__.py
pdx/agent/__init__.py
pdx/agent/config.py
pdx/agent/metadata.py
pdx/agent/tester.py
pdx/cache/__init__.py
pdx/cache/cache.py
pdx/cache/in_memory_cache.py
pdx/cache/utils.py
pdx/cli.py
pdx/commands/__init__.py
pdx/commands/create.py
pdx/exceptions.py
pdx/logger.py
pdx/metadata.py
pdx/models/__init__.py
pdx/models/anthropic/__init__.py
pdx/models/anthropic/client.py
pdx/models/anthropic/completion.py
pdx/models/anthropic/constants.py
pdx/models/anthropic/exceptions.py
pdx/models/api_client.py
pdx/models/cohere/__init__.py
pdx/models/cohere/client.py
pdx/models/cohere/exceptions.py
pdx/models/cohere/generation.py
pdx/models/config.py
pdx/models/metadata.py
pdx/models/model.py
pdx/models/openai/__init__.py
pdx/models/openai/client.py
pdx/models/openai/completion.py
pdx/models/openai/exceptions.py
pdx/models/utils.py
pdx/prompt/__init__.py
pdx/prompt/config.py
pdx/prompt/prompt_chain.py
pdx/prompt/prompt_session.py
pdx/prompt/prompt_template.py
pdx/prompt/prompt_tree.py
pdx/settings.py
pdx/templates/__init__.py
pdx/templates/simple/Readme.md
pdx/templates/simple/__init__.py
pdx/templates/simple/templates/1_prompt.defaults.yaml
pdx/templates/simple/templates/1_prompt.jinja
pdx/templates/simple/tests/test_1.yaml
pdx/utils/__init__.py
pdx/utils/rw.py
pdx/worker/__init__.py
pdx/worker/metadata.py
pdx-0.7.0.dist-info/LICENSE
pdx-0.7.0.dist-info/METADATA
pdx-0.7.0.dist-info/WHEEL
pdx-0.7.0.dist-info/entry_points.txt
pdx-0.7.0.dist-info/RECORD
